vassapi/__init__.py
vassapi/base.py
vassapi/const.py
vassapi/exceptions.py
vassapi/models.py
vassapi/version.py
vassapi-0.2.0.dist-info/LICENSE
vassapi-0.2.0.dist-info/METADATA
vassapi-0.2.0.dist-info/WHEEL
vassapi-0.2.0.dist-info/top_level.txt
vassapi-0.2.0.dist-info/RECORD
