Metadata-Version: 2.1
Name: vassapi
Version: 0.2.0
Summary: Voice Assistant Python client
Home-page: https://github.com/voice-assistant-org/voice-assistant-client
Author: Vadim Titov
Author-email: titov.hse@gmail.com
License: UNKNOWN
Project-URL: Bug Tracker, https://github.com/voice-assistant-org/voice-assistant-client/issues
Platform: UNKNOWN
Classifier: Programming Language :: Python :: 3
Classifier: Operating System :: OS Independent
Classifier: Development Status :: 3 - Alpha
Classifier: Topic :: Home Automation
Requires-Python: >=3.7
License-File: LICENSE
Requires-Dist: httpx (<1,>=0.22.0)
Provides-Extra: test
Requires-Dist: pytest ; extra == 'test'
